{"key":"1Urnp2gy9zQ","title":"Pesadilla en la cocina USA 2x07 - Jack's Waterfront","description":"Pesadilla en la cocina USA - Gordon Ramsay Kitchen Nightmares. Septimo episodio.Segunda temporada Jack's Waterfront St. Clair Shores, Michigan Noviembre 6, 2008. Kitchen Nightmares (conocido en España como Pesadilla en la cocina) es un programa de televisión que emite FOX, presentado por el restaurador británico Gordon Ramsay. En cada capítulo, el chef viaja por Estados Unidos para visitar restaurantes con problemas de todo tipo, con la intención de ayudar a sus dueños a reflotar el negocio. El formato está basado en el programa británico Ramsay's Kitchen Nightmares, enfocado en cocinas del Reino Unido y que el propio Gordon Ramsay presentó desde 2004 hasta 2007. El primer episodio de la versión norteamericana se emitió el 19 de septiembre de 2007, y desde entonces se han producido cinco temporadas. Actualmente, la serie continúa en emisión.","publishedDate":"Published on Apr 17, 2013","viewCount":24862,"noOfLikes":59,"noOfDislikes":2,"relatedURL":["/watch?v=nFqgRit5ecM","/watch?v=0fLSMfmeo28","/watch?v=fDNqCCyzz9Y","/watch?v=AjIIK0wsHDY","/watch?v=SUaYMmLuDuI","/watch?v=IbVg10gSIYM","/watch?v=5OBHfpKwh6o","/watch?v=S05mDNMSF0E&list=PL5X-WIYpQrX6pWWobvTe38byjbfHBbG1P","/watch?v=5sKgqiB0VgU","/watch?v=aFKUEP1fPsg","/watch?v=NHQEKUGXF3o","/watch?v=HwSPgXzDXP8","/watch?v=wgfZz7U1-a8","/watch?v=hFYq8U1VTQs","/watch?v=r-l6fM63cCA","/watch?v=a-WMIT-11EI","/watch?v=McxN60geaKQ","/watch?v=Bx2shGyTHHk","/watch?v=iHo3H9-KQzo","/watch?v=N_SMmx7k554","/watch?v=xJtDYC51hto","/watch?v=0Nt6kDFB_hg","/watch?v=KBaEKryzJP0","/watch?v=FnXR1Euue9c","/watch?v=baWCN2lrzcU","/watch?v=DGioenjexzA","/watch?v=XfdKu7zHqMo","/watch?v=GX4eUnpbBi4","/watch?v=Jk_Su06FgP0","/watch?v=rdMjkQRJoI8","/watch?v=J_ZtmzahZyQ","/watch?v=UXDKQJFLeXI","/watch?v=rGInAmgRsVw","/watch?v=-bxgk6RZZlU","/watch?v=93Z7EoGBHEU","/watch?v=Gknerm71J7c","/watch?v=rzSSSqSkPII","/watch?v=Ym4lhgcDYrc","/watch?v=5PeDdgExVjk","/watch?v=kEy-y_rQ86M"],"category":"Entertainment","licence":"Standard YouTube License","comments":[],"latitude":0.0,"longitude":0.0,"duration":"PT42M20S","channelID":"UC7ONP7zdvPW-mRX4DnYoagA","authorYTURL":"http://www.youtube.com/user/AmorDeCocina","authorGPlusURL":"","isFamilyFriendly":true,"regionAllowed":"AD,AE,AF,AG,AI,AL,AM,AO,AQ,AR,AS,AT,AU,AW,AX,AZ,BA,BB,BD,BE,BF,BG,BH,BI,BJ,BL,BM,BN,BO,BQ,BR,BS,BT,BV,BW,BY,BZ,CA,CC,CD,CF,CG,CH,CI,CK,CL,CM,CN,CO,CR,CU,CV,CW,CX,CY,CZ,DE,DJ,DK,DM,DO,DZ,EC,EE,EG,EH,ER,ES,ET,FI,FJ,FK,FM,FO,FR,GA,GD,GE,GF,GH,GI,GL,GM,GN,GP,GQ,GR,GS,GT,GU,GW,GY,HK,HM,HN,HR,HT,HU,ID,IL,IN,IO,IQ,IR,IS,IT,JM,JO,JP,KE,KG,KH,KI,KM,KN,KP,KR,KW,KY,KZ,LA,LB,LC,LI,LK,LR,LS,LT,LU,LV,LY,MA,MC,MD,ME,MF,MG,MH,MK,ML,MM,MN,MO,MP,MQ,MR,MS,MT,MU,MV,MW,MX,MY,MZ,NA,NC,NE,NF,NG,NI,NL,NO,NP,NR,NU,NZ,OM,PA,PE,PF,PG,PH,PK,PL,PM,PN,PR,PS,PT,PW,PY,QA,RE,RO,RS,RU,RW,SA,SB,SC,SD,SE,SG,SH,SI,SJ,SK,SL,SM,SN,SO,SR,SS,ST,SV,SX,SY,SZ,TC,TD,TF,TG,TH,TJ,TK,TL,TM,TN,TO,TR,TT,TV,TW,TZ,UA,UG,UM,US,UY,UZ,VA,VC,VE,VG,VI,VN,VU,WF,WS,YE,YT,ZA,ZM,ZW","isPaid":false,"unlisted":false}