{"key":"cwWcTvG8f0A","title":"The Great Gatsby Trailer","description":"More Trailers: http://goo.gl/ipMFQx The Great Gatsby Official Trailer (2013) - Leonardo DiCaprio Movie [HD] A Midwestern war veteran finds himself drawn to the past and lifestyle of his millionaire neighbor. Director: Baz Luhrmann Writers: Baz Luhrmann, Craig Pearce Stars: Leonardo DiCaprio, Joel Edgerton, Tobey Maguire","publishedDate":"Published on Aug 21, 2013","viewCount":261,"noOfLikes":1,"noOfDislikes":0,"relatedURL":["/watch?v=61oxkOk4jy0","/watch?v=OcN_OYcq40Q","/watch?v=PZs3iQshmOI","/watch?v=fU9UXn8o_6I","/watch?v=wEAgLAe6YoU","/watch?v=x9_Qsb0mPFk","/watch?v=tr3XK9FkNCY","/watch?v=LVHU_YWV3e4","/watch?v=QflekFEDv9Y","/watch?v=6rFnewqh6qU","/watch?v=bw2bkISm0Ys","/watch?v=oKLep6H6_kE","/watch?v=nIewKn6EnAs","/watch?v=4Y3wDN_OlxE","/watch?v=9AXywjN_H24","/watch?v=Y0k2_IkQtKY","/watch?v=jXgb7j41fig","/watch?v=Omx9w4081MM","/watch?v=whM4wMUhN0U","/watch?v=3-tdK2aJpww","/watch?v=Omx9w4081MM","/watch?v=Y0k2_IkQtKY","/watch?v=o2bw-2W_LPo","/watch?v=ZWir6wUkPtw","/watch?v=qmVeVl7WsNI","/watch?v=vR0fAHSYjAg","/watch?v=Gs3ckKuUZP0","/watch?v=p0l6a__1xcI","/watch?v=whM4wMUhN0U","/watch?v=c_3bob4nPdM","/watch?v=jKs6tUxVC7M","/watch?v=siD4bUtiF0g","/watch?v=hxH1LwvPGTc","/watch?v=QoNEBRiRteY","/watch?v=RRiQlscErao","/watch?v=GK9RxfibScA","/watch?v=V31kaf46R54","/watch?v=jmF5BamOyqs","/watch?v=P_aAt6kFius","/watch?v=hAESe4Dc0HY"],"category":"Film & Animation","licence":"Standard YouTube License","comments":[],"latitude":0.0,"longitude":0.0,"duration":"PT2M37S","channelID":"UCgZn1uBn_U9MslpMNdpkAqA","authorYTURL":"http://www.youtube.com/user/zbyhdmt","authorGPlusURL":"https://plus.google.com/100888484621662721238","isFamilyFriendly":true,"regionAllowed":"AD,AE,AF,AG,AI,AL,AM,AO,AQ,AR,AS,AT,AU,AW,AX,AZ,BA,BB,BD,BE,BF,BG,BH,BI,BJ,BL,BM,BN,BO,BQ,BR,BS,BT,BV,BW,BY,BZ,CA,CC,CD,CF,CG,CH,CI,CK,CL,CM,CN,CO,CR,CU,CV,CW,CX,CY,CZ,DE,DJ,DK,DM,DO,DZ,EC,EE,EG,EH,ER,ES,ET,FI,FJ,FK,FM,FO,FR,GA,GB,GD,GE,GF,GG,GH,GI,GL,GM,GN,GP,GQ,GR,GS,GT,GU,GW,GY,HK,HM,HN,HR,HT,HU,ID,IE,IL,IM,IN,IO,IQ,IR,IS,IT,JE,JM,JO,JP,KE,KG,KH,KI,KM,KN,KP,KR,KW,KY,KZ,LA,LB,LC,LI,LK,LR,LS,LT,LU,LV,LY,MA,MC,MD,ME,MF,MG,MH,MK,ML,MM,MN,MO,MP,MQ,MR,MS,MT,MU,MV,MW,MX,MY,MZ,NA,NC,NE,NF,NG,NI,NL,NO,NP,NR,NU,NZ,OM,PA,PE,PF,PG,PH,PK,PL,PM,PN,PR,PS,PT,PW,PY,QA,RE,RO,RS,RU,RW,SA,SB,SC,SD,SE,SG,SH,SI,SJ,SK,SL,SM,SN,SO,SR,SS,ST,SV,SX,SY,SZ,TC,TD,TF,TG,TH,TJ,TK,TL,TM,TN,TO,TR,TT,TV,TW,TZ,UA,UG,UM,US,UY,UZ,VA,VC,VE,VG,VI,VN,VU,WF,WS,YE,YT,ZA,ZM,ZW","isPaid":false,"unlisted":false}