{"key":"kmDYt79im7s","title":"Pakistani Funny Clip With The People of Pakistan","description":"Please Watch And Subscribe For All Pakistani Ary digital HUM Tv Dramas in High Quality","publishedDate":"Published on Aug 14, 2012","viewCount":13950,"noOfLikes":7,"noOfDislikes":2,"relatedURL":["/watch?v=T_wkMWsbn08","/watch?v=jqul8gipqjI","/watch?v=PhnCAAzdjuE","/watch?v=xR2PbhbIbtM","/watch?v=0odgGuoDTwI","/watch?v=vXQg5AjGRiA","/watch?v=3qTN3Y-AL7M","/watch?v=kYpKO-ZU7lI","/watch?v=Gi-hQOc5WKs","/watch?v=ERKJFTQimSI","/watch?v=yVC96AlNgM8","/watch?v=RIczs3Fr_Ao","/watch?v=IP3v0ehFLRo","/watch?v=-7TkkLZrssU","/watch?v=gNEcZ83nzfw","/watch?v=PTMD7L5gmIw","/watch?v=MBam4Avtkcc","/watch?v=PIe6kGxRWlo","/watch?v=EEpFV9ymbUk","/watch?v=AdW6hx6LNGg","/watch?v=J-qHrGciOpY","/watch?v=Qd8t3UCWhiA","/watch?v=HKvUwMY-_Ck","/watch?v=Q8J3wbQwOBM","/watch?v=ZKTSF-48BLc","/watch?v=pBB8OHoZL7E","/watch?v=rCPyH8bfaDU","/watch?v=EQLqSpfrh4A","/watch?v=AdW6hx6LNGg","/watch?v=sFKBfgaHaso","/watch?v=q_JrirzCPRM","/watch?v=vMwxHBqBifI","/watch?v=Trg1yXQrWQ8","/watch?v=h3bWsanTsps","/watch?v=TxH6t5y_sVs","/watch?v=IP3v0ehFLRo","/watch?v=6ljuYVV9Ggg","/watch?v=xkdXq0id8Ns","/watch?v=P5eb2NHlrqw","/watch?v=PTMD7L5gmIw"],"category":"Film & Animation","licence":"Standard YouTube License","comments":[],"latitude":0.0,"longitude":0.0,"duration":"PT5M4S","channelID":"UC1YJTFS7-IjXVZk5UGVQ0MQ","authorYTURL":"http://www.youtube.com/user/BiggBoss5HD","authorGPlusURL":"https://plus.google.com/102865197327615553934","isFamilyFriendly":true,"regionAllowed":"AD,AE,AF,AG,AI,AL,AM,AO,AQ,AR,AS,AT,AU,AW,AX,AZ,BA,BB,BD,BE,BF,BG,BH,BI,BJ,BL,BM,BN,BO,BQ,BR,BS,BT,BV,BW,BY,BZ,CA,CC,CD,CF,CG,CH,CI,CK,CL,CM,CN,CO,CR,CU,CV,CW,CX,CY,CZ,DE,DJ,DK,DM,DO,DZ,EC,EE,EG,EH,ER,ES,ET,FI,FJ,FK,FM,FO,FR,GA,GB,GD,GE,GF,GG,GH,GI,GL,GM,GN,GP,GQ,GR,GS,GT,GU,GW,GY,HK,HM,HN,HR,HT,HU,ID,IE,IL,IM,IN,IO,IQ,IR,IS,IT,JE,JM,JO,JP,KE,KG,KH,KI,KM,KN,KP,KR,KW,KY,KZ,LA,LB,LC,LI,LK,LR,LS,LT,LU,LV,LY,MA,MC,MD,ME,MF,MG,MH,MK,ML,MM,MN,MO,MP,MQ,MR,MS,MT,MU,MV,MW,MX,MY,MZ,NA,NC,NE,NF,NG,NI,NL,NO,NP,NR,NU,NZ,OM,PA,PE,PF,PG,PH,PK,PL,PM,PN,PR,PS,PT,PW,PY,QA,RE,RO,RS,RU,RW,SA,SB,SC,SD,SE,SG,SH,SI,SJ,SK,SL,SM,SN,SO,SR,SS,ST,SV,SX,SY,SZ,TC,TD,TF,TG,TH,TJ,TK,TL,TM,TN,TO,TR,TT,TV,TW,TZ,UA,UG,UM,US,UY,UZ,VA,VC,VE,VG,VI,VN,VU,WF,WS,YE,YT,ZA,ZM,ZW","isPaid":false,"unlisted":false}