{"key":"w-YohAcO67k","title":"Тодор Живков - Всяка неделя","description":"Тодор Живков - Всяка неделя","publishedDate":"Published on Aug 25, 2012","viewCount":33986,"noOfLikes":99,"noOfDislikes":8,"relatedURL":["/watch?v=H9jrLR1WyOk","/watch?v=tNI9v5VI1t8","/watch?v=JKyMmsplAN4","/watch?v=9ZZbr7agpnY","/watch?v=fIuh90bgIJM","/watch?v=rGFnjPSQ-aU","/watch?v=VOsbymyIxMs","/watch?v=LhCDpIKM3UY","/watch?v=_GMW2xBqSfo","/watch?v=5WxXIVJIYV0","/watch?v=iWep-CumjdY","/watch?v=sSs75XTYLK8&list=PLF98B94510C9A926C","/watch?v=EgpM47yOY_A","/watch?v=JHcxjpchPA4","/watch?v=9AipR-IJaNE","/watch?v=LNeK8wzir40","/watch?v=y4qrEAWSS3M","/watch?v=G3_cBDwyBIQ","/watch?v=65D66yj_wcE","/watch?v=XxKHOqs4egs","/watch?v=n2Z0-ZPIJLI","/watch?v=caTqHb9HJr0","/watch?v=1H8zpPA58-k","/watch?v=AKiPJp4XldQ","/watch?v=9Ffkdz34lFY","/watch?v=bIVR4rZn4do","/watch?v=4-lQCSkbr6A","/watch?v=cLw_VRmXYW0","/watch?v=3MRbE9ORcjs","/watch?v=G_QyRWEZNY8","/watch?v=AK89uNbWbZM","/watch?v=H37WmEk5bI4","/watch?v=rSuPMEkAnZc","/watch?v=Gt1uEa2e8R0","/watch?v=-8KmShpi_2A","/watch?v=qeCibI5kVQs","/watch?v=dXgtSlZpfv8","/watch?v=6xhsLT8VI5Y","/watch?v=ceGLBmhjuxY","/watch?v=bZha8DZH03M"],"category":"News & Politics","licence":"Standard YouTube License","comments":[],"latitude":0.0,"longitude":0.0,"duration":"PT13M51S","channelID":"UCBjxs9rpME2vWdH4kZzVd8w","authorYTURL":"http://www.youtube.com/user/Nittvinge","authorGPlusURL":"https://plus.google.com/116401195248499387161","isFamilyFriendly":true,"regionAllowed":"AD,AE,AF,AG,AI,AL,AM,AO,AQ,AR,AS,AT,AU,AW,AX,AZ,BA,BB,BD,BE,BF,BG,BH,BI,BJ,BL,BM,BN,BO,BQ,BR,BS,BT,BV,BW,BY,BZ,CA,CC,CD,CF,CG,CH,CI,CK,CL,CM,CN,CO,CR,CU,CV,CW,CX,CY,CZ,DE,DJ,DK,DM,DO,DZ,EC,EE,EG,EH,ER,ES,ET,FI,FJ,FK,FM,FO,FR,GA,GB,GD,GE,GF,GG,GH,GI,GL,GM,GN,GP,GQ,GR,GS,GT,GU,GW,GY,HK,HM,HN,HR,HT,HU,ID,IE,IL,IM,IN,IO,IQ,IR,IS,IT,JE,JM,JO,JP,KE,KG,KH,KI,KM,KN,KP,KR,KW,KY,KZ,LA,LB,LC,LI,LK,LR,LS,LT,LU,LV,LY,MA,MC,MD,ME,MF,MG,MH,MK,ML,MM,MN,MO,MP,MQ,MR,MS,MT,MU,MV,MW,MX,MY,MZ,NA,NC,NE,NF,NG,NI,NL,NO,NP,NR,NU,NZ,OM,PA,PE,PF,PG,PH,PK,PL,PM,PN,PR,PS,PT,PW,PY,QA,RE,RO,RS,RU,RW,SA,SB,SC,SD,SE,SG,SH,SI,SJ,SK,SL,SM,SN,SO,SR,SS,ST,SV,SX,SY,SZ,TC,TD,TF,TG,TH,TJ,TK,TL,TM,TN,TO,TR,TT,TV,TW,TZ,UA,UG,UM,US,UY,UZ,VA,VC,VE,VG,VI,VN,VU,WF,WS,YE,YT,ZA,ZM,ZW","isPaid":false,"unlisted":false}