{"key":"xCiwEioXJ_s","title":"Jutsus Episode 1","description":"this video will teach u the hand seals for some cool jutsus i researched. it took me literly hours to put it together and make this video....","publishedDate":"Uploaded on Aug 28, 2009","viewCount":156138,"noOfLikes":225,"noOfDislikes":35,"relatedURL":["/watch?v=cWAGpbZoEx4","/watch?v=Pb2M62dGP5g","/watch?v=beKjqJ2tYmg","/watch?v=bGs4FB9f5Ts","/watch?v=7FBRYWZhU-M","/watch?v=5ny74Mbu28w","/watch?v=aiZyRPc3y1M","/watch?v=oZhUDKWbQwU","/watch?v=vWhzjCEgiEg","/watch?v=sM9XzKATHsU","/watch?v=Vkyf5ymc3Ns","/watch?v=9f_63SbRAzI","/watch?v=YqEdNf8yefc","/watch?v=UnItc6xDbfs","/watch?v=MyDRwK1LFV8","/watch?v=HkFpIsvtajU&list=PL77833E2EE5F3D2F9","/watch?v=hQNrqVrLbB8","/watch?v=YSIYAVRJOTg","/watch?v=wshh3cpfYm8","/watch?v=cUaJMZDPtEg","/watch?v=XtO4xIvXRH8","/watch?v=v2-EcyQGr68","/watch?v=_jLIt-2C3yk","/watch?v=9wQS3jGT2LE","/watch?v=Oth2yECmx9A","/watch?v=MmJrp_Yullc","/watch?v=w5T15GTD4gs","/watch?v=vRisy6EiBAw","/watch?v=awWEriWzRHI","/watch?v=B8bb4FNrPP0","/watch?v=jqTw-1YF7rc","/watch?v=2ad7biFq5N4","/watch?v=ErTvfi5mdLQ","/watch?v=KekfuSK2boA","/watch?v=piUakL7C1Ao","/watch?v=aSuJg3eBFhY","/watch?v=IiHSqhklEfo","/watch?v=3LZqO7i0kWw","/watch?v=GO78cOXWAEg","/watch?v=T9Urgv6i_OQ"],"category":"People & Blogs","licence":"Standard YouTube License","comments":[],"latitude":0.0,"longitude":0.0,"duration":"PT4M29S","channelID":"UCb5WvlOMIiV3Z1_dZ-xM40g","authorYTURL":"http://www.youtube.com/user/SasukeItachiUchiha25","authorGPlusURL":"","isFamilyFriendly":true,"regionAllowed":"AD,AE,AF,AG,AI,AL,AM,AO,AQ,AR,AS,AT,AU,AW,AX,AZ,BA,BB,BD,BE,BF,BG,BH,BI,BJ,BL,BM,BN,BO,BQ,BR,BS,BT,BV,BW,BY,BZ,CA,CC,CD,CF,CG,CH,CI,CK,CL,CM,CN,CO,CR,CU,CV,CW,CX,CY,CZ,DE,DJ,DK,DM,DO,DZ,EC,EE,EG,EH,ER,ES,ET,FI,FJ,FK,FM,FO,FR,GA,GB,GD,GE,GF,GG,GH,GI,GL,GM,GN,GP,GQ,GR,GS,GT,GU,GW,GY,HK,HM,HN,HR,HT,HU,ID,IE,IL,IM,IN,IO,IQ,IR,IS,IT,JE,JM,JO,JP,KE,KG,KH,KI,KM,KN,KP,KR,KW,KY,KZ,LA,LB,LC,LI,LK,LR,LS,LT,LU,LV,LY,MA,MC,MD,ME,MF,MG,MH,MK,ML,MM,MN,MO,MP,MQ,MR,MS,MT,MU,MV,MW,MX,MY,MZ,NA,NC,NE,NF,NG,NI,NL,NO,NP,NR,NU,NZ,OM,PA,PE,PF,PG,PH,PK,PL,PM,PN,PR,PS,PT,PW,PY,QA,RE,RO,RS,RU,RW,SA,SB,SC,SD,SE,SG,SH,SI,SJ,SK,SL,SM,SN,SO,SR,SS,ST,SV,SX,SY,SZ,TC,TD,TF,TG,TH,TJ,TK,TL,TM,TN,TO,TR,TT,TV,TW,TZ,UA,UG,UM,US,UY,UZ,VA,VC,VE,VG,VI,VN,VU,WF,WS,YE,YT,ZA,ZM,ZW","isPaid":false,"unlisted":false}