{"key":"ZvdLYt3IBPs","title":"Defense's Closing: Part 3","description":"Part 3 of the defense's closing argument in the Casey Anthony murder trial.","publishedDate":"Published on Jul 3, 2011","viewCount":15439,"noOfLikes":31,"noOfDislikes":5,"relatedURL":["/watch?v=6ha_eacgw7I","/watch?v=WBxyPl4lJFk","/watch?v=SvJIbem1WFQ","/watch?v=qEDeUE33xGw","/watch?v=4MzfQoKPAsY","/watch?v=Ww2sUueMcVI","/watch?v=0GSQK0XO08U","/watch?v=UnJu_k7bmjI","/watch?v=wHk9qxAg0ic","/watch?v=cPACxU6wE5M","/watch?v=mi3GvJJactk","/watch?v=uMZ47Fmq-Ts","/watch?v=xlYeQgyR128","/watch?v=S0hUe1ecKr8","/watch?v=3ebTAc1dvsY","/watch?v=rKiR4r3R0eU","/watch?v=ANndx586Msk","/watch?v=_Jch3NgFyzA","/watch?v=0lpbCD3t7sg","/watch?v=Md6FrUAHnEY","/watch?v=vHdJ2xAoE0U","/watch?v=oILRGY4obtA","/watch?v=ybNUo2EM7b8","/watch?v=6U7ubz0qL-o","/watch?v=hW01h_pwkJ4","/watch?v=CM9HWPCCX88","/watch?v=Ry0swmCWnnY","/watch?v=NYch3GrpRm4","/watch?v=Gxxdr-bodOA","/watch?v=Ut2Cv64uY-A","/watch?v=z3xJi0Lu_fc","/watch?v=O1ZsXCOx_hk","/watch?v=zpnDk8J6wJg","/watch?v=kYXnqlDNa8o","/watch?v=CdES3DiC18E","/watch?v=4SH6pJ4u_9o","/watch?v=0lJ_-PJdQkk","/watch?v=vN0qIQ-MdGs","/watch?v=VGhg5jP1U5Y","/watch?v=fHhoi1OmmoY"],"category":"News & Politics","licence":"Standard YouTube License","comments":[],"latitude":0.0,"longitude":0.0,"duration":"PT25M17S","channelID":"UCD9nZ3qeRGbPuHJaJduiQxA","authorYTURL":"http://www.youtube.com/user/weshtv","authorGPlusURL":"https://plus.google.com/118180778386292717726","isFamilyFriendly":true,"regionAllowed":"AD,AE,AF,AG,AI,AL,AM,AO,AQ,AR,AS,AT,AU,AW,AX,AZ,BA,BB,BD,BE,BF,BG,BH,BI,BJ,BL,BM,BN,BO,BQ,BR,BS,BT,BV,BW,BY,BZ,CA,CC,CD,CF,CG,CH,CI,CK,CL,CM,CN,CO,CR,CU,CV,CW,CX,CY,CZ,DE,DJ,DK,DM,DO,DZ,EC,EE,EG,EH,ER,ES,ET,FI,FJ,FK,FM,FO,FR,GA,GB,GD,GE,GF,GG,GH,GI,GL,GM,GN,GP,GQ,GR,GS,GT,GU,GW,GY,HK,HM,HN,HR,HT,HU,ID,IE,IL,IM,IN,IO,IQ,IR,IS,IT,JE,JM,JO,JP,KE,KG,KH,KI,KM,KN,KP,KR,KW,KY,KZ,LA,LB,LC,LI,LK,LR,LS,LT,LU,LV,LY,MA,MC,MD,ME,MF,MG,MH,MK,ML,MM,MN,MO,MP,MQ,MR,MS,MT,MU,MV,MW,MX,MY,MZ,NA,NC,NE,NF,NG,NI,NL,NO,NP,NR,NU,NZ,OM,PA,PE,PF,PG,PH,PK,PL,PM,PN,PR,PS,PT,PW,PY,QA,RE,RO,RS,RU,RW,SA,SB,SC,SD,SE,SG,SH,SI,SJ,SK,SL,SM,SN,SO,SR,SS,ST,SV,SX,SY,SZ,TC,TD,TF,TG,TH,TJ,TK,TL,TM,TN,TO,TR,TT,TV,TW,TZ,UA,UG,UM,US,UY,UZ,VA,VC,VE,VG,VI,VN,VU,WF,WS,YE,YT,ZA,ZM,ZW","isPaid":false,"unlisted":false}