{"key":"bjgFH01k0gU","title":"Jennifer Lopez - Dance Again ft. Pitbull","description":"Music video by Jennifer Lopez Feat. Pitbull performing Dance Again. (C) 2012 Epic Records, a division of Sony Music Entertainment","publishedDate":"Published on Apr 5, 2012","viewCount":297409679,"noOfLikes":644355,"noOfDislikes":49446,"relatedURL":["/watch?v=bjgFH01k0gU&list=RDbjgFH01k0gU","/watch?v=t4H_Zoh7G5A","/watch?v=IgLcQmlN2Xg","/watch?v=BofL1AaiTjo","/watch?v=z5W7DVFKrcs","/watch?v=HBxt_v0WF6Y","/watch?v=CdXesX6mYUE","/watch?v=6XbIuSLaCnk","/watch?v=5jlI4uzZGjU","/watch?v=c4oiEhf9M04","/watch?v=Xmap94TcDNs","/watch?v=SmM0653YvXU","/watch?v=4kGvlESGvbs","/watch?v=tg00YEETFzg","/watch?v=Ys7-6_t7OEQ","/watch?v=SeIJmciN8mo","/watch?v=JRfuAukYTKg","/watch?v=cAP6Aaymg0E&list=PL5F9760B328AD5C94","/watch?v=7zp1TbLFPp8","/watch?v=3rgwIp6D3ow","/watch?v=3rgwIp6D3ow","/watch?v=UJtB55MaoD0","/watch?v=kYtGl1dX5qI","/watch?v=lWA2pjMjpBs","/watch?v=MntbN1DdEP0","/watch?v=hnCQlCqjvqo","/watch?v=eQWG8BVeryU","/watch?v=XXywgkY2O5U","/watch?v=fwK7ggA3-bU","/watch?v=tDq3fNew1rU","/watch?v=a5irTX82olg","/watch?v=6BTjG-dhf5s","/watch?v=uuwfgXD8qV8","/watch?v=fWNaR-rxAic","/watch?v=SbUBMklQSVU","/watch?v=bpOR_HuHRNs","/watch?v=t5Sd5c4o9UM","/watch?v=k0BWlvnBmIE","/watch?v=1zfzka5VwRc","/watch?v=d19eBjpP2Aw"],"category":"Music","licence":"Standard YouTube License","comments":[],"latitude":0.0,"longitude":0.0,"duration":"PT4M27S","channelID":"UCx1f1u4XlFFr0YgqF3wB4lQ","authorYTURL":"http://www.youtube.com/user/JenniferLopezVEVO","authorGPlusURL":"https://plus.google.com/109023093550499781465","isFamilyFriendly":true,"regionAllowed":"AD,AE,AF,AG,AI,AL,AM,AO,AQ,AR,AS,AT,AU,AW,AX,AZ,BA,BB,BD,BE,BF,BG,BH,BI,BJ,BL,BM,BN,BO,BR,BS,BT,BV,BW,BY,BZ,CA,CC,CD,CF,CG,CH,CI,CK,CL,CM,CN,CO,CR,CU,CV,CX,CY,CZ,DJ,DK,DM,DO,DZ,EC,EE,EG,EH,ER,ES,ET,FI,FJ,FK,FM,FO,FR,GA,GB,GD,GE,GF,GG,GH,GI,GL,GM,GN,GP,GQ,GR,GS,GT,GU,GW,GY,HK,HM,HN,HR,HT,HU,ID,IE,IL,IM,IN,IO,IQ,IR,IS,IT,JE,JM,JO,JP,KE,KG,KH,KI,KM,KN,KP,KR,KW,KY,KZ,LA,LB,LC,LI,LK,LR,LS,LT,LU,LV,LY,MA,MC,MD,ME,MF,MG,MH,MK,ML,MM,MN,MO,MP,MQ,MR,MS,MT,MU,MV,MW,MX,MY,MZ,NA,NC,NE,NF,NG,NI,NL,NO,NP,NR,NU,NZ,OM,PA,PE,PF,PG,PH,PK,PL,PM,PN,PR,PS,PT,PW,PY,QA,RE,RO,RS,RU,RW,SA,SB,SC,SD,SE,SG,SH,SI,SJ,SK,SL,SM,SN,SO,SR,ST,SV,SY,SZ,TC,TD,TF,TG,TH,TJ,TK,TL,TM,TN,TO,TR,TT,TV,TW,TZ,UA,UG,UM,US,UY,UZ,VA,VC,VE,VG,VI,VN,VU,WF,WS,YE,YT,ZA,ZM,ZW","isPaid":false,"unlisted":false}