{"key":"dHnRN5JTDF4","title":"Go Kart With Street Bike Engine!! Holy Sh#t","description":"One off racing go kart with a suzuki gn400 engine This should be on everybody's bucket list.","publishedDate":"Published on Aug 25, 2012","viewCount":1552540,"noOfLikes":2028,"noOfDislikes":235,"relatedURL":["/watch?v=RZMdUYN-8z0","/watch?v=nRRZMovC6u8","/watch?v=IND3eAI3YZk","/watch?v=YBZLsyh5QvI","/watch?v=9QeJ0k_QDh8","/watch?v=VqYNRGfflPk","/watch?v=WaA3aQ9SPSI","/watch?v=ww-hg5IRmRo","/watch?v=BZDwL2xuzkU","/watch?v=z7buTCULLeY","/watch?v=SGO2MRGesow","/watch?v=AGFXZmoy2bk","/watch?v=eYXg78r6yBA","/watch?v=apd1KBjLV8k","/watch?v=m39yL3TYb-g","/watch?v=K5CYmklIx5Q","/watch?v=InvF9e5kyjo","/watch?v=0t8iwKLebAQ","/watch?v=-vFKK0g8HC8","/watch?v=6AqUV0aYbZ8","/watch?v=7dZmroqr8yI","/watch?v=ZAV2uQrnEFM","/watch?v=z0ish567ZgU","/watch?v=Djx80P9v-Jc","/watch?v=znY1vNvlREc","/watch?v=0_juysg5U3I","/watch?v=2n0Pm4AQ-kk","/watch?v=Ax429NlLwJk","/watch?v=lCWp05fwlrE","/watch?v=YcpFq-ZsJSA","/watch?v=JKCtifrhMEM","/watch?v=RGi-Dv0N9zY","/watch?v=0ZOzyg-A2JY","/watch?v=Gigl8_CpJIg","/watch?v=ou2PLolvw0I","/watch?v=tJel8dJuPH8","/watch?v=BzKshx36h1g","/watch?v=nMRhus76p5M","/watch?v=3Ys-isAxpMY","/watch?v=_nQW0jsqv4Y"],"category":"Autos & Vehicles","licence":"Standard YouTube License","comments":[],"latitude":0.0,"longitude":0.0,"duration":"PT1M8S","channelID":"UCSSLKN5AWIJS4qiWIJxF78Q","authorYTURL":"http://www.youtube.com/user/78vwrabbit","authorGPlusURL":"https://plus.google.com/106910692795528537683","isFamilyFriendly":true,"regionAllowed":"AD,AE,AF,AG,AI,AL,AM,AO,AQ,AR,AS,AT,AU,AW,AX,AZ,BA,BB,BD,BE,BF,BG,BH,BI,BJ,BL,BM,BN,BO,BQ,BR,BS,BT,BV,BW,BY,BZ,CA,CC,CD,CF,CG,CH,CI,CK,CL,CM,CN,CO,CR,CU,CV,CW,CX,CY,CZ,DE,DJ,DK,DM,DO,DZ,EC,EE,EG,EH,ER,ES,ET,FI,FJ,FK,FM,FO,FR,GA,GB,GD,GE,GF,GG,GH,GI,GL,GM,GN,GP,GQ,GR,GS,GT,GU,GW,GY,HK,HM,HN,HR,HT,HU,ID,IE,IL,IM,IN,IO,IQ,IR,IS,IT,JE,JM,JO,JP,KE,KG,KH,KI,KM,KN,KP,KR,KW,KY,KZ,LA,LB,LC,LI,LK,LR,LS,LT,LU,LV,LY,MA,MC,MD,ME,MF,MG,MH,MK,ML,MM,MN,MO,MP,MQ,MR,MS,MT,MU,MV,MW,MX,MY,MZ,NA,NC,NE,NF,NG,NI,NL,NO,NP,NR,NU,NZ,OM,PA,PE,PF,PG,PH,PK,PL,PM,PN,PR,PS,PT,PW,PY,QA,RE,RO,RS,RU,RW,SA,SB,SC,SD,SE,SG,SH,SI,SJ,SK,SL,SM,SN,SO,SR,SS,ST,SV,SX,SY,SZ,TC,TD,TF,TG,TH,TJ,TK,TL,TM,TN,TO,TR,TT,TV,TW,TZ,UA,UG,UM,US,UY,UZ,VA,VC,VE,VG,VI,VN,VU,WF,WS,YE,YT,ZA,ZM,ZW","isPaid":false,"unlisted":false}