{"key":"dvf--10EYXw","title":"3OH!3 - STARSTRUKK (Feat. Katy Perry) [OFFICIAL MUSIC VIDEO]","description":"© 2009 Photo Finish Records From the album WANT - Available Now: http://pfr.ec/WANTalbum http://3OH3music.com/video To get more music from 3OH!3, go here: http://pfr.ec/3OH3MusicStore","publishedDate":"Uploaded on Oct 28, 2009","viewCount":88641132,"noOfLikes":281106,"noOfDislikes":9718,"relatedURL":["/watch?v=dvf--10EYXw&list=RDdvf--10EYXw","/watch?v=AYC2FUutdKA","/watch?v=mdB3Oyd5HtU","/watch?v=-iGQ2JydtRk","/watch?v=5iWxD0GZVVk","/watch?v=3taEuL4EHAg","/watch?v=Ix5z1bRz4Sc","/watch?v=tAp9BKosZXs","/watch?v=1-pUaogoX5o","/watch?v=kYtGl1dX5qI","/watch?v=aCyGvGEtOwc","/watch?v=eiiU-Fky18s","/watch?v=u4FF6MpcsRw","/watch?v=HpyZEzrDf4c","/watch?v=kn6-c223DUU","/watch?v=uxUATkpMQ8A","/watch?v=1Uw6ZkbsAH8","/watch?v=0KSOMA3QBU0","/watch?v=Bg59q4puhmg","/watch?v=RTxKtHCkEVk&list=PLEB5ED46B43EA8A32","/watch?v=6g6g2mvItp4","/watch?v=U5rLz5AZBIA","/watch?v=T3E9Wjbq44E","/watch?v=DksSPZTZES0","/watch?v=EVBsypHzF3U","/watch?v=k0BWlvnBmIE","/watch?v=ykW4rtW2eu0","/watch?v=F57P9C4SAW4","/watch?v=QGJuMBdaqIw","/watch?v=M11SvDtPBhA","/watch?v=F3o53tjxiNQ","/watch?v=VuNIsY6JdUw","/watch?v=KlyXNRrsk4A","/watch?v=8PTDv_szmL0","/watch?v=vc6vs-l5dkc","/watch?v=fwK7ggA3-bU","/watch?v=YUtHjOvPKT0","/watch?v=t5Sd5c4o9UM","/watch?v=1G4isv_Fylg","/watch?v=41i4uCWST_U"],"category":"Music","licence":"Standard YouTube License","comments":[],"latitude":0.0,"longitude":0.0,"duration":"PT3M42S","channelID":"UCx3PiIfsGF0Px-vY5OciMDg","authorYTURL":"http://www.youtube.com/user/photofinishrecords","authorGPlusURL":"https://plus.google.com/105709576196693704454","isFamilyFriendly":true,"regionAllowed":"AD,AL,AR,AT,AU,BA,BE,BG,BO,BQ,BR,CA,CH,CL,CN,CO,CU,CW,CY,CZ,DE,DK,EE,EG,ES,FI,FR,GB,GR,HK,HR,HU,ID,IE,IL,IN,IR,IS,IT,JP,KP,KR,LT,LU,LV,MC,ME,MK,MT,MX,MY,NG,NL,NO,NZ,PE,PG,PH,PL,PT,PY,RO,RS,RU,SE,SG,SI,SK,SS,SX,SY,TH,TR,TW,UA,US,UY,VE,ZA","isPaid":false,"unlisted":false}