{"key":"EG4JztsFEM4","title":"Freeway, The Jacka and Joe Blow Freestyle On Sway In The Morning","description":"Freeway, The Jacka and Joe Blow jump on the mic for an exclusive freestyle on Sway In The Morning. Subscribe to our page: http://bit.ly/SVsBQC TWITTER: http://twitter.com/RealSway http://twitter.com/TheHappyHourwHB http://twitter.com/DJWonder http://twitter.com/ItsTracyG FACEBOOK: https://www.facebook.com/SwayCalloway WEBSITE: http://swaysuniverse.com http://ishootnyc.com Sways Universe, Sway In The Morning, Rap, Hip-Hop, Freestyles, Interviews, Live, Concert, Performances, Actors, Athletes, Singers, Celebrities, Television, FIlm, Shade45, 5 Fingers of Death, i shoot nyc, ishootnyc","publishedDate":"Published on Sep 18, 2014","viewCount":31147,"noOfLikes":307,"noOfDislikes":22,"relatedURL":["/watch?v=z33tZsSoZ2Q","/watch?v=o1IylErzKts","/watch?v=8rHuoukXPCI","/watch?v=9p-DRTbYUyM","/watch?v=Y_z_3tKoOfg","/watch?v=baqu9I9_pUk","/watch?v=zE2nHIwoe2s","/watch?v=t4-jvOKBeMU","/watch?v=_au4nuMkYsE","/watch?v=fQNUVdYIU1s","/watch?v=V1IA6fb3oJE","/watch?v=hUURgRCuHu4","/watch?v=tej0swtR1gI","/watch?v=lWLleo7NKh8","/watch?v=aLjgUcPwa64","/watch?v=kckQIwZcDY0","/watch?v=NfM_fb1onoI","/watch?v=PtN96sIVlFQ","/watch?v=S78tT_YxF_c","/watch?v=h3YbH4QUNWY","/watch?v=PtN96sIVlFQ","/watch?v=z2dlKX5SKDg","/watch?v=kecZ9ql0B3c","/watch?v=EzqdWEuYmIg","/watch?v=bGq95Fadve8","/watch?v=XCVxCTBhpUk","/watch?v=uBNiAPBrD1w","/watch?v=Bw7rfuGF8m0","/watch?v=JwtkjE7g7KQ","/watch?v=5utSZAReyuU","/watch?v=08WN_xvB0AA","/watch?v=U4qPM8k2Mkc","/watch?v=6qbQNPUEaLs","/watch?v=PvA-DdXDj1U","/watch?v=MiUt_iIp-4g","/watch?v=0fYIHy__RbM","/watch?v=0RM-ClpB9fk","/watch?v=Dq9ZddZG06Q","/watch?v=ywRo8p1SBSI","/watch?v=8JODrt88hvI"],"category":"Entertainment","licence":"Standard YouTube License","comments":[],"latitude":0.0,"longitude":0.0,"duration":"PT4M11S","channelID":"UCuS96jkLKpTaGB_OWnwZV_A","authorYTURL":"http://www.youtube.com/user/SwaysUniverse","authorGPlusURL":"https://plus.google.com/106755786950081155597","isFamilyFriendly":true,"regionAllowed":"AD,AE,AF,AG,AI,AL,AM,AO,AQ,AR,AS,AT,AU,AW,AX,AZ,BA,BB,BD,BE,BF,BG,BH,BI,BJ,BL,BM,BN,BO,BQ,BR,BS,BT,BV,BW,BY,BZ,CA,CC,CD,CF,CG,CH,CI,CK,CL,CM,CN,CO,CR,CU,CV,CW,CX,CY,CZ,DE,DJ,DK,DM,DO,DZ,EC,EE,EG,EH,ER,ES,ET,FI,FJ,FK,FM,FO,FR,GA,GB,GD,GE,GF,GG,GH,GI,GL,GM,GN,GP,GQ,GR,GS,GT,GU,GW,GY,HK,HM,HN,HR,HT,HU,ID,IE,IL,IM,IN,IO,IQ,IR,IS,IT,JE,JM,JO,JP,KE,KG,KH,KI,KM,KN,KP,KR,KW,KY,KZ,LA,LB,LC,LI,LK,LR,LS,LT,LU,LV,LY,MA,MC,MD,ME,MF,MG,MH,MK,ML,MM,MN,MO,MP,MQ,MR,MS,MT,MU,MV,MW,MX,MY,MZ,NA,NC,NE,NF,NG,NI,NL,NO,NP,NR,NU,NZ,OM,PA,PE,PF,PG,PH,PK,PL,PM,PN,PR,PS,PT,PW,PY,QA,RE,RO,RS,RU,RW,SA,SB,SC,SD,SE,SG,SH,SI,SJ,SK,SL,SM,SN,SO,SR,SS,ST,SV,SX,SY,SZ,TC,TD,TF,TG,TH,TJ,TK,TL,TM,TN,TO,TR,TT,TV,TW,TZ,UA,UG,UM,US,UY,UZ,VA,VC,VE,VG,VI,VN,VU,WF,WS,YE,YT,ZA,ZM,ZW","isPaid":false,"unlisted":false}