{"key":"GGtcJCzB9cU","title":"Deadmau5 - Moar Ghosts 'n' Stuff (Hard Intro Mix 2011)","description":"Deadmau5 -Moar Ghosts 'n' Stuff Hard Intro Mix 2011 By Xadani9 xadani9-Facebook and downloads: http://www.facebook.com/xadani90 xadani9 soundcloud: http://soundcloud.com/xadani9 Covert Art by Xadani9, download link: http://i54.tinypic.com/14kiiwy.jpg","publishedDate":"Uploaded on Apr 4, 2011","viewCount":6608322,"noOfLikes":35824,"noOfDislikes":603,"relatedURL":["/watch?v=GGtcJCzB9cU&list=RDGGtcJCzB9cU","/watch?v=YnwfTHpnGLY","/watch?v=yuR1rVVf358","/watch?v=rQxAJLBAIH4","/watch?v=prX3--rtqXk","/watch?v=MEQMkzjcLEA","/watch?v=_9IBbMW2o_o","/watch?v=tKi9Z-f6qX4","/watch?v=gDndZn0YPdI","/watch?v=zK1mLIeXwsQ","/watch?v=Hr2Bc5qMhE4","/watch?v=A67GQgoiinM","/watch?v=YTcopp-mpmo","/watch?v=y7tI1E6kp0o","/watch?v=X2Z9Cn_9awU","/watch?v=VzTShCCo1CM","/watch?v=h7ArUgxtlJs","/watch?v=3Gb3faOzvBk","/watch?v=AYw-t4uDblM","/watch?v=uiUAq4aVTjY","/watch?v=x1IJMJl6Vfc","/watch?v=YnEUfeiSKt0","/watch?v=WCpfVPY4J6I","/watch?v=5fYA2kd3cyQ","/watch?v=NBp9mNOFDLk","/watch?v=SX2Gd-kqV5s","/watch?v=Cx5qYm6kvw0","/watch?v=bXWk-aInsow","/watch?v=k6lVhGeyXuw","/watch?v=bn5CtUEgKMo","/watch?v=cpJupfR6CMo","/watch?v=yOZmCQWZ5tw","/watch?v=yU3tatx2fOM","/watch?v=-e_3Cg9GZFU","/watch?v=3l5N2pabiME","/watch?v=4ky-gventQo","/watch?v=tkw88OIUMWg","/watch?v=pb-EwykPTv8","/watch?v=QV8eiSA4vqc","/watch?v=3ywya8Q7mvQ"],"category":"Music","licence":"Standard YouTube License","comments":[],"latitude":0.0,"longitude":0.0,"duration":"PT5M38S","channelID":"UCLIf9o7Y563KGymZjoCeleg","authorYTURL":"http://www.youtube.com/user/MontainsBMX","authorGPlusURL":"https://plus.google.com/104729844950842468776","isFamilyFriendly":true,"regionAllowed":"AD,AE,AF,AG,AI,AL,AM,AO,AQ,AR,AS,AT,AU,AW,AX,AZ,BA,BB,BD,BE,BF,BG,BH,BI,BJ,BL,BM,BN,BO,BQ,BR,BS,BT,BV,BW,BY,BZ,CA,CC,CD,CF,CG,CH,CI,CK,CL,CM,CN,CO,CR,CU,CV,CW,CX,CY,CZ,DJ,DK,DM,DO,DZ,EC,EE,EG,EH,ER,ES,ET,FI,FJ,FK,FM,FO,FR,GA,GB,GD,GE,GF,GG,GH,GI,GL,GM,GN,GP,GQ,GR,GS,GT,GU,GW,GY,HK,HM,HN,HR,HT,HU,ID,IE,IL,IM,IN,IO,IQ,IR,IS,IT,JE,JM,JO,JP,KE,KG,KH,KI,KM,KN,KP,KR,KW,KY,KZ,LA,LB,LC,LI,LK,LR,LS,LT,LU,LV,LY,MA,MC,MD,ME,MF,MG,MH,MK,ML,MM,MN,MO,MP,MQ,MR,MS,MT,MU,MV,MW,MX,MY,MZ,NA,NC,NE,NF,NG,NI,NL,NO,NP,NR,NU,NZ,OM,PA,PE,PF,PG,PH,PK,PL,PM,PN,PR,PS,PT,PW,PY,QA,RE,RO,RS,RU,RW,SA,SB,SC,SD,SE,SG,SH,SI,SJ,SK,SL,SM,SN,SO,SR,SS,ST,SV,SX,SY,SZ,TC,TD,TF,TG,TH,TJ,TK,TL,TM,TN,TO,TR,TT,TV,TW,TZ,UA,UG,UM,US,UY,UZ,VA,VC,VE,VG,VI,VN,VU,WF,WS,YE,YT,ZA,ZM,ZW","isPaid":false,"unlisted":false}