{"key":"HjYtomSkI8I","title":"CCR - 21st Anniversary Ultimate Collection - Full Album","description":"CCR - 21st Anniversary Ultimate Collection - Full Album Track List 01 - Bad Moon Rising 02 - Lookin Out My Back Door 03 - I Put A Spell On You 04 - Hey Tonight 05 - Good Golly Miss Molly 06 - I Heard It Through The Grapevine 07 - Someday Never Comes 08 - Suzie Q 09 - Fortunate Son 10 - Ooby Dooby 11 - Lodi 12 - Green River 13 - Who'll Stop The Rain 14 - Proud Mary 15 - Down On The Corner 16 - The Midnight Special 17 - Run Through The Jungle 18 - Have You Ever Seen The Rain 19 - Travelin Band 20. - Sweet Hictchhiker 21 - As Long As I Can See The Light 22 - Up Around The Bend 23 - Molina 24 - Born On The Bayou","publishedDate":"Published on Jan 4, 2013","viewCount":64762,"noOfLikes":172,"noOfDislikes":6,"relatedURL":["/watch?v=HjYtomSkI8I&list=RDHjYtomSkI8I","/watch?v=6jFn9T1ge2g","/watch?v=JacHyPaEwDc&list=PL160A8517216029F7","/watch?v=fzEZdy216gw","/watch?v=2w9QM9JmTWQ","/watch?v=KcbmqOaGqWc","/watch?v=b3gm44oyLmY","/watch?v=KHPR4Lia15A","/watch?v=n0QYCRDauLk","/watch?v=-2V6qGX7VRs","/watch?v=P6gjFtly_nI","/watch?v=myKvdzkYvoc","/watch?v=7FMI7-ZF78U","/watch?v=PvLChtYDVQ8","/watch?v=jrIbHCSLBlI","/watch?v=_yQtDuHJ3LE","/watch?v=1uheZMxpwok","/watch?v=gEcClL2ZNgE","/watch?v=3sjLbxj1niw","/watch?v=O3a_8j8413g","/watch?v=5PIBMLvcAzc","/watch?v=P0-ZKaWVYSk","/watch?v=2ABlQXmbcp8","/watch?v=5SI8tbgnYuc","/watch?v=DvVznAb9-Ss","/watch?v=h8lWNUjHEYI","/watch?v=6BRMnrkbvso","/watch?v=xU5e7898CD4","/watch?v=V9Pqs0bMNac","/watch?v=iVPDjdbmZ28","/watch?v=Is_UwhTJm7o","/watch?v=EGokf35GOLc","/watch?v=uVKpmDouCGk","/watch?v=c6rQthKld-g","/watch?v=LlIMQTLGelY","/watch?v=ZiBfy8GB2Nk","/watch?v=ejSdXJphcHo","/watch?v=Lrj5Kxdzouc","/watch?v=cHkv2GGjYVU","/watch?v=AfaBlGBBVf0"],"category":"Music","licence":"Standard YouTube License","comments":[],"latitude":0.0,"longitude":0.0,"duration":"PT73M57S","channelID":"UCfSUNniUKxOn-4cUkxbEmmg","authorYTURL":"http://www.youtube.com/user/LeFreak70s","authorGPlusURL":"","isFamilyFriendly":true,"regionAllowed":"AD,AE,AF,AG,AI,AL,AM,AO,AQ,AR,AS,AT,AU,AW,AX,AZ,BA,BB,BD,BE,BF,BG,BH,BI,BJ,BL,BM,BN,BO,BQ,BR,BS,BT,BV,BW,BY,BZ,CA,CC,CD,CF,CG,CH,CI,CK,CL,CM,CN,CO,CR,CU,CV,CW,CX,CY,CZ,DJ,DK,DM,DO,DZ,EC,EE,EG,EH,ER,ES,ET,FI,FJ,FK,FM,FO,FR,GA,GB,GD,GE,GF,GG,GH,GI,GL,GM,GN,GP,GQ,GR,GS,GT,GU,GW,GY,HK,HM,HN,HR,HT,HU,ID,IE,IL,IM,IN,IO,IQ,IR,IS,IT,JE,JM,JO,JP,KE,KG,KH,KI,KM,KN,KP,KR,KW,KY,KZ,LA,LB,LC,LI,LK,LR,LS,LT,LU,LV,LY,MA,MC,MD,ME,MF,MG,MH,MK,ML,MM,MN,MO,MP,MQ,MR,MS,MT,MU,MV,MW,MX,MY,MZ,NA,NC,NE,NF,NG,NI,NL,NO,NP,NR,NU,NZ,OM,PA,PE,PF,PG,PH,PK,PL,PM,PN,PR,PS,PT,PW,PY,QA,RE,RO,RS,RU,RW,SA,SB,SC,SD,SE,SG,SH,SI,SJ,SK,SL,SM,SN,SO,SR,SS,ST,SV,SX,SY,SZ,TC,TD,TF,TG,TH,TJ,TK,TL,TM,TN,TO,TR,TT,TV,TW,TZ,UA,UG,UM,US,UY,UZ,VA,VC,VE,VG,VI,VN,VU,WF,WS,YE,YT,ZA,ZM,ZW","isPaid":false,"unlisted":false}