{"key":"R7hRW9xQRjI","title":"Call of Duty: Black Ops 2 Soundtrack - \"Imma Try it Out\" by Skrillex ft. Alvin Risk 10 Hours","description":"Song made by Skrillex and Alvin Risk and remixed by Jack Wall for Call of Duty: Black Ops 2.","publishedDate":"Published on Feb 1, 2013","viewCount":568122,"noOfLikes":4142,"noOfDislikes":181,"relatedURL":["/watch?v=XG8b7WhANNA","/watch?v=dPPnnKCeCzE","/watch?v=4R4vZOfwSe4","/watch?v=eaV18O4MHaY","/watch?v=KzRwV2tjZLM","/watch?v=whTuOnHNNRM","/watch?v=RJav8fxLaBc","/watch?v=5sjuVFkA35E","/watch?v=SyVntSZlaC8","/watch?v=KUS_N7-ukJM&list=PLoA940ndDlR2XAZULiX6spDAkOwUh63xQ","/watch?v=mGxhk2SP4cc","/watch?v=8rGiKv1xkE0","/watch?v=Ex2efbdv0_4","/watch?v=ekrxf1cu0j8","/watch?v=cVmpdRcxChg","/watch?v=2sw2Ek9iJKE","/watch?v=ygVdI65ef-I","/watch?v=BnmUuhaEeFo","/watch?v=mMvq44Bvr-w","/watch?v=5u7YmansZGs","/watch?v=AHnslBhmR7Q","/watch?v=VZs0eBGlU1M","/watch?v=UAlfKzLFU0I","/watch?v=dLyH94jNau0","/watch?v=vJjBkoQD2ng","/watch?v=LUNCqP13VOs","/watch?v=cRLFFlvyuS0","/watch?v=rx5XyspHldk","/watch?v=xcO5fgypjFY","/watch?v=nX6bF22T1yo","/watch?v=gNN6KGxPNhM","/watch?v=vMJ18xDS1f8","/watch?v=vBdCdntp1uI","/watch?v=c8tfsPb-NSg","/watch?v=zkcdNR605d4","/watch?v=S5RgSxsyIb8","/watch?v=zgIlc2dBFZk","/watch?v=O2okXeHNXQI","/watch?v=RvIt88eRCog","/watch?v=YbB9Z0aAEC8"],"category":"Gaming","licence":"Standard YouTube License","comments":[],"latitude":0.0,"longitude":0.0,"duration":"PT600M40S","channelID":"UCFDi7jNWX11YHYm09yoXidw","authorYTURL":"http://www.youtube.com/user/TheRealHungryGrox","authorGPlusURL":"https://plus.google.com/108297020809809814234","isFamilyFriendly":true,"regionAllowed":"AD,AE,AF,AG,AI,AL,AM,AO,AQ,AR,AS,AT,AU,AW,AX,AZ,BA,BB,BD,BE,BF,BG,BH,BI,BJ,BL,BM,BN,BO,BQ,BR,BS,BT,BV,BW,BY,BZ,CA,CC,CD,CF,CG,CH,CI,CK,CL,CM,CN,CO,CR,CU,CV,CW,CX,CY,CZ,DE,DJ,DK,DM,DO,DZ,EC,EE,EG,EH,ER,ES,ET,FI,FJ,FK,FM,FO,FR,GA,GB,GD,GE,GF,GG,GH,GI,GL,GM,GN,GP,GQ,GR,GS,GT,GU,GW,GY,HK,HM,HN,HR,HT,HU,ID,IE,IL,IM,IN,IO,IQ,IR,IS,IT,JE,JM,JO,JP,KE,KG,KH,KI,KM,KN,KP,KR,KW,KY,KZ,LA,LB,LC,LI,LK,LR,LS,LT,LU,LV,LY,MA,MC,MD,ME,MF,MG,MH,MK,ML,MM,MN,MO,MP,MQ,MR,MS,MT,MU,MV,MW,MX,MY,MZ,NA,NC,NE,NF,NG,NI,NL,NO,NP,NR,NU,NZ,OM,PA,PE,PF,PG,PH,PK,PL,PM,PN,PR,PS,PT,PW,PY,QA,RE,RO,RS,RU,RW,SA,SB,SC,SD,SE,SG,SH,SI,SJ,SK,SL,SM,SN,SO,SR,SS,ST,SV,SX,SY,SZ,TC,TD,TF,TG,TH,TJ,TK,TL,TM,TN,TO,TR,TT,TV,TW,TZ,UA,UG,UM,US,UY,UZ,VA,VC,VE,VG,VI,VN,VU,WF,WS,YE,YT,ZA,ZM,ZW","isPaid":false,"unlisted":false}