{"key":"VitKvID-uvY","title":"BOB MARLEY FEAT LAURYN HILL \"Turn your lights down low\"","description":"BOB MARLEY FEAT LAURYN HILL \"Turn your lights down low\"","publishedDate":"Uploaded on Feb 29, 2008","viewCount":2838402,"noOfLikes":13246,"noOfDislikes":93,"relatedURL":["/watch?v=VitKvID-uvY&list=RDVitKvID-uvY","/watch?v=2I5C7nREnxM","/watch?v=K69A1lL1PHQ","/watch?v=_KpeCk6NyZU","/watch?v=FJ5BXfXUYwM","/watch?v=lF0TzvImsl0","/watch?v=dNk3R23Twgw","/watch?v=cE-bnWqLqxE","/watch?v=jkBTMEsY2Sk&list=PLCF32F45129D9B6FA","/watch?v=TzEq3qMLToM","/watch?v=NW55FRXlPEs","/watch?v=rNajx1cD5T4","/watch?v=6xcNOZLFt4o","/watch?v=E00q3cKwuvM","/watch?v=3QhneRiJeyY","/watch?v=LlZydtG3xqI","/watch?v=ePMM28uGIjI","/watch?v=YfWjTBfklWk","/watch?v=CHekNnySAfM","/watch?v=T6QKqFPRZSA","/watch?v=RTQL42onK08","/watch?v=aIXyKmElvv8","/watch?v=sRf_r_dz-vM","/watch?v=uhAvVZQ2Sx4","/watch?v=brWmS8As9Wk","/watch?v=jGqrvn3q1oo","/watch?v=k7Pk5YMkEcg","/watch?v=ktgHNJ4RmIY","/watch?v=0h9FExyTWVE","/watch?v=UiF_G13VM5o","/watch?v=MPlb9HoOCxs","/watch?v=lkfKGzX7rEw","/watch?v=5Ry3JIwCxhg","/watch?v=R8GCc8OhTz8","/watch?v=Xme0WC3OZ9k","/watch?v=i3TlLCm7V8g","/watch?v=8hfSfj-MlzA","/watch?v=Ai2VnZc1ZnY","/watch?v=OFGgbT_VasI","/watch?v=YF4cjKyxxc8"],"category":"Music","licence":"Standard YouTube License","comments":[],"latitude":0.0,"longitude":0.0,"duration":"PT4M24S","channelID":"UCGBendhLfztZi7csRcvWiaw","authorYTURL":"http://www.youtube.com/user/wikigirl2212","authorGPlusURL":"","isFamilyFriendly":true,"regionAllowed":"AD,AE,AF,AG,AI,AL,AM,AO,AQ,AR,AS,AT,AU,AW,AX,AZ,BA,BB,BD,BE,BF,BG,BH,BI,BJ,BL,BM,BN,BO,BQ,BR,BS,BT,BV,BW,BY,BZ,CA,CC,CD,CF,CG,CH,CI,CK,CL,CM,CN,CO,CR,CU,CV,CW,CX,CY,CZ,DJ,DK,DM,DO,DZ,EC,EE,EG,EH,ER,ES,ET,FI,FJ,FK,FM,FO,FR,GA,GB,GD,GE,GF,GG,GH,GI,GL,GM,GN,GP,GQ,GR,GS,GT,GU,GW,GY,HK,HM,HN,HR,HT,HU,ID,IE,IL,IM,IN,IO,IQ,IR,IS,IT,JE,JM,JO,JP,KE,KG,KH,KI,KM,KN,KP,KR,KW,KY,KZ,LA,LB,LC,LI,LK,LR,LS,LT,LU,LV,LY,MA,MC,MD,ME,MF,MG,MH,MK,ML,MM,MN,MO,MP,MQ,MR,MS,MT,MU,MV,MW,MX,MY,MZ,NA,NC,NE,NF,NG,NI,NL,NO,NP,NR,NU,NZ,OM,PA,PE,PF,PG,PH,PK,PL,PM,PN,PR,PS,PT,PW,PY,QA,RE,RO,RS,RU,RW,SA,SB,SC,SD,SE,SG,SH,SI,SJ,SK,SL,SM,SN,SO,SR,SS,ST,SV,SX,SY,SZ,TC,TD,TF,TG,TH,TJ,TK,TL,TM,TN,TO,TR,TT,TV,TW,TZ,UA,UG,UM,US,UY,UZ,VA,VC,VE,VG,VI,VN,VU,WF,WS,YE,YT,ZA,ZM,ZW","isPaid":false,"unlisted":false}