{"key":"x56Y6eFuQVk","title":"The Wind Blows (Skrillex Remix), by AAR.","description":"remixed song by http://www.myspace.com/skrillex // http://www.myspace.com/sonny original song by The All-American Rejects. lyrics: Shake-the-thought-of-you-and-- Me together I've got to breathe Can't take that from me Cause it's all that you left that's mine You had to leave And that's all I can see But you told me your love was blind I know there are times You're so impossible that I should sign a waiver And you will find Someone worth walking on when you ask me to go I'll leave when the wind-- I'll leave when the wind blows Take a breath and there it goes I'll be outside of your window I'll pass by but I'll go slow I'll leave when the wind blows There was a day You threw our love away Then you passed it to someone new You wanna stay But since you wanna play We can finally say we're through I know there are times You're so impossible and you ask me to go I'll leave when the wind-- Shake-the-thought-of-you-and-- Me together As I lay in solitude Oh, what's a boy supposed to do I shake the very thought of you Me together, I remember Late nights when I stayed up late All I do is wait and wait You're never coming home to me That's the hardest thing to see I'll leave when the wind-- I'll leave when the wind blows Take a breath and there it goes I'll be outside of your window I'll pass by but I'll go slow I'll leave when the wind blows There was a day You threw our love away Then you passed it to someone new You wanna stay But since you wanna play We can finally say we're through I'll leave when the wind blows Take a breath and there it goes I'll be outside of your window I'll pass by but I'll go slow I'll leave when the wind blows You can scream, there's just echoes Pass outside of your window You'll be sad that you let me go On every face you'll ever know And everywhere you ever go You'll feel when the wind blows Shake-the-thought-of-you-and-- Me together","publishedDate":"Uploaded on Aug 15, 2009","viewCount":550115,"noOfLikes":2403,"noOfDislikes":78,"relatedURL":["/watch?v=x56Y6eFuQVk&list=RDx56Y6eFuQVk","/watch?v=YJVmu6yttiw","/watch?v=CKxdFKP0Ajw","/watch?v=mMvq44Bvr-w","/watch?v=AZP8Aa02ST8","/watch?v=PE3IslWaB4E","/watch?v=-e_3Cg9GZFU","/watch?v=PE3IslWaB4E&list=PL93691DB265F41070","/watch?v=zJuSl8AD9HA","/watch?v=SX5ilsGwc64","/watch?v=_vdG3aCncTc","/watch?v=5bv4fD4u6sE","/watch?v=XypiQqUMEnI","/watch?v=6ngYQcxBjmU","/watch?v=2ugS1nQqKeY","/watch?v=_99MMG0Kr_0","/watch?v=YnwfTHpnGLY","/watch?v=8PYmQfHzzCw","/watch?v=7VQC486qQgk","/watch?v=cC6zXxibuQA","/watch?v=zkcdNR605d4","/watch?v=UzHFi-CbXko","/watch?v=i-gyZ35074k","/watch?v=k6lVhGeyXuw","/watch?v=uxUATkpMQ8A","/watch?v=WSeNSzJ2-Jw","/watch?v=gPDcwjJ8pLg","/watch?v=NI2b7qXUlnE","/watch?v=L7Azyv_6VC4","/watch?v=C1hjsVLcGFc","/watch?v=gXgcysWD6C8","/watch?v=yfdAGkjHGac","/watch?v=KtypSRcwIhA","/watch?v=XleOkGsYgO8","/watch?v=1UWgRwVRbxc","/watch?v=0nrmWz3RVQA","/watch?v=kMycYI-lA9g","/watch?v=bn5CtUEgKMo","/watch?v=HAfFfqiYLp0","/watch?v=Td__NqATVcs"],"category":"Music","licence":"Standard YouTube License","comments":[],"latitude":0.0,"longitude":0.0,"duration":"PT4M56S","channelID":"UC306ZFhIIks9keSbvEalu3Q","authorYTURL":"http://www.youtube.com/user/totalxcrap","authorGPlusURL":"https://plus.google.com/105969292078864456232","isFamilyFriendly":true,"regionAllowed":"AD,AE,AF,AG,AI,AL,AM,AO,AQ,AR,AS,AT,AU,AW,AX,AZ,BA,BB,BD,BE,BF,BG,BH,BI,BJ,BL,BM,BN,BO,BQ,BR,BS,BT,BV,BW,BY,BZ,CA,CC,CD,CF,CG,CH,CI,CK,CL,CM,CN,CO,CR,CU,CV,CW,CX,CY,CZ,DJ,DK,DM,DO,DZ,EC,EE,EG,EH,ER,ES,ET,FI,FJ,FK,FM,FO,FR,GA,GB,GD,GE,GF,GG,GH,GI,GL,GM,GN,GP,GQ,GR,GS,GT,GU,GW,GY,HK,HM,HN,HR,HT,HU,ID,IE,IL,IM,IN,IO,IQ,IR,IS,IT,JE,JM,JO,JP,KE,KG,KH,KI,KM,KN,KP,KR,KW,KY,KZ,LA,LB,LC,LI,LK,LR,LS,LT,LU,LV,LY,MA,MC,MD,ME,MF,MG,MH,MK,ML,MM,MN,MO,MP,MQ,MR,MS,MT,MU,MV,MW,MX,MY,MZ,NA,NC,NE,NF,NG,NI,NL,NO,NP,NR,NU,NZ,OM,PA,PE,PF,PG,PH,PK,PL,PM,PN,PR,PS,PT,PW,PY,QA,RE,RO,RS,RU,RW,SA,SB,SC,SD,SE,SG,SH,SI,SJ,SK,SL,SM,SN,SO,SR,SS,ST,SV,SX,SY,SZ,TC,TD,TF,TG,TH,TJ,TK,TL,TM,TN,TO,TR,TT,TV,TW,TZ,UA,UG,UM,US,UY,UZ,VA,VC,VE,VG,VI,VN,VU,WF,WS,YE,YT,ZA,ZM,ZW","isPaid":false,"unlisted":false}