{"key":"zK1mLIeXwsQ","title":"deadmau5 & Kaskade - I Remember (HQ)","description":"Pick up all deadmau5's music here: http://goo.gl/CorVS \"I Remember\" is track #7 from the first deadmau5 album \"Random Album Title\" on Ultra Records - ultrarecords.com","publishedDate":"Uploaded on Sep 19, 2008","viewCount":23963305,"noOfLikes":94080,"noOfDislikes":2574,"relatedURL":["/watch?v=zK1mLIeXwsQ&list=RDzK1mLIeXwsQ","/watch?v=YnwfTHpnGLY","/watch?v=YTcopp-mpmo","/watch?v=ZVFR3k0xMtc","/watch?v=2KTxNTxTtm0","/watch?v=QV8eiSA4vqc","/watch?v=ZKDJcHFrCOE","/watch?v=Mn69LJ0239E","/watch?v=2QTtTLtOWfg&list=PL65DE2DD1BB4681F2","/watch?v=_9IBbMW2o_o","/watch?v=C1p8HlgoRHE","/watch?v=O2jj3YbgX_w","/watch?v=XjTSpgAm8QM","/watch?v=8-bU5zKYSBQ","/watch?v=A67GQgoiinM","/watch?v=hChhgMT5wq0","/watch?v=MEQMkzjcLEA","/watch?v=xcury71mJbc","/watch?v=-0ZjPHeHCvo","/watch?v=a2PM5iTlmRE","/watch?v=8D6ZeZvFqhw","/watch?v=3l5N2pabiME","/watch?v=gDndZn0YPdI","/watch?v=t7RyZ4Zf4Dk","/watch?v=6A7UMUaXIxI","/watch?v=w4mKtIjiKZU","/watch?v=NgBQJDQbeFA","/watch?v=xwpj9UANXo4","/watch?v=OsJSwGc4lsA","/watch?v=atFTgQOF-cU","/watch?v=f9qavey27Kc","/watch?v=Qg-nIAnUZwE","/watch?v=GGtcJCzB9cU","/watch?v=Hr2Bc5qMhE4","/watch?v=IPDSiL1nH0k","/watch?v=kvp2xW0-uZU","/watch?v=YnEUfeiSKt0","/watch?v=SNXuQJo94pc","/watch?v=YSANu-oAHHQ","/watch?v=KzwJNdAH9KE"],"category":"Music","licence":"Standard YouTube License","comments":[],"latitude":0.0,"longitude":0.0,"duration":"PT9M54S","channelID":"UC4rasfm9J-X4jNl9SvXp8xA","authorYTURL":"http://www.youtube.com/user/UltraRecords","authorGPlusURL":"https://plus.google.com/117425916497743763701","isFamilyFriendly":true,"regionAllowed":"AD,AE,AF,AG,AI,AL,AM,AO,AQ,AR,AS,AT,AU,AW,AX,AZ,BA,BB,BD,BE,BF,BG,BH,BI,BJ,BL,BM,BN,BO,BQ,BR,BS,BT,BV,BW,BY,BZ,CA,CC,CD,CF,CG,CH,CI,CK,CL,CM,CN,CO,CR,CU,CV,CW,CX,CY,CZ,DE,DJ,DK,DM,DO,DZ,EC,EE,EG,EH,ER,ES,ET,FI,FJ,FK,FM,FO,FR,GA,GB,GD,GE,GF,GG,GH,GI,GL,GM,GN,GP,GQ,GR,GS,GT,GU,GW,GY,HK,HM,HN,HR,HT,HU,ID,IE,IL,IM,IN,IO,IQ,IR,IS,IT,JE,JM,JO,JP,KE,KG,KH,KI,KM,KN,KP,KR,KW,KY,KZ,LA,LB,LC,LI,LK,LR,LS,LT,LU,LV,LY,MA,MC,MD,ME,MF,MG,MH,MK,ML,MM,MN,MO,MP,MQ,MR,MS,MT,MU,MV,MW,MX,MY,MZ,NA,NC,NE,NF,NG,NI,NL,NO,NP,NR,NU,NZ,OM,PA,PE,PF,PG,PH,PK,PL,PM,PN,PR,PS,PT,PW,PY,QA,RE,RO,RS,RU,RW,SA,SB,SC,SD,SE,SG,SH,SI,SJ,SK,SL,SM,SN,SO,SR,SS,ST,SV,SX,SY,SZ,TC,TD,TF,TG,TH,TJ,TK,TL,TM,TN,TO,TR,TT,TV,TW,TZ,UA,UG,UM,US,UY,UZ,VA,VC,VE,VG,VI,VN,VU,WF,WS,YE,YT,ZA,ZM,ZW","isPaid":false,"unlisted":false}