{"key":"ocgaUkG5CtM","title":"Arrow - Unthinkable Trailer","description":"It will come down to kill or be killed! Don't miss the season finale of Arrow with a special sneak peek at The Flash Wednesday at 8/7c! Like this video? Check out the Arrow STUNTS SERIES http://www.youtube.com/watch?v=aDaAI9... SUBSCRIBE to The CW https://youtube.com/subscription_cent... ABOUT ARROW After a violent shipwreck, billionaire playboy Oliver Queen (Stephen Amell) was missing and presumed dead for five years before being discovered alive on a remote island in the Pacific. He returned home to Starling City, welcomed by his devoted mother Moira (Susanna Thompson), beloved sister Thea (Willa Holland) and former flame Laurel Lance (Katie Cassidy). With the aid of his trusted chauffeur/bodyguard John Diggle (David Ramsey), the computer-hacking skills of Felicity Smoak (Emily Bett Rickards) and the occasional, reluctant assistance of former police detective, now beat cop, Quentin Lance (Paul Blackthorne), Oliver has been waging a one-man war on crime. FOLLOW ARROW http://www.cwtv.com/shows/arrow http://www.facebook.com/CWArrow http://www.twitter.com/CW_Arrow Find The CW here: http://cwtv.com/ http://www.facebook.com/TheCW http://twitter.com/cw_network http://instagram.com/thecw http://plus.google.com/+thecw/ http://cwnetwork.tumblr.com/","publishedDate":"Published on May 12, 2014","viewCount":529686,"noOfLikes":1660,"noOfDislikes":10,"relatedURL":["/watch?v=5t1jcQjEsaw","/watch?v=uEZQUcjG6AY","/watch?v=TodrKT_c-Tk","/watch?v=ptI8evHNPSo","/watch?v=UWfd0boBMGM","/watch?v=4RHQo30_r7I","/watch?v=mASg0eh5LOU","/watch?v=ndvErSCLQIA","/watch?v=K_xNvdptsXY","/watch?v=iKFpc0s6i1Q","/watch?v=uPE2oBnzROY","/watch?v=4xD0junWlFc","/watch?v=Yj0l7iGKh8g","/watch?v=dm1n_Kh58Bc","/watch?v=uQDwN7e1Y9M","/watch?v=fig6nRJXqXE","/watch?v=f4y9vvQEcnQ","/watch?v=Img49q_NTIU","/watch?v=0d1zpt6k5OI","/watch?v=FspuwbI3fKM"],"category":"","comments":[],"latitude":0.0,"longitude":0.0,"duration":"PT0M31S","channelID":"UCPWQWav6BpPvtanCtloXkiw","authorYTURL":"http://www.youtube.com/user/CWtelevision","authorGPlusURL":"https://plus.google.com/102014282623377856806","isFamilyFriendly":true,"regionAllowed":"AD,AE,AF,AG,AI,AL,AM,AO,AQ,AR,AS,AT,AU,AW,AX,AZ,BA,BB,BD,BE,BF,BG,BH,BI,BJ,BL,BM,BN,BO,BQ,BR,BS,BT,BV,BW,BY,BZ,CA,CC,CD,CF,CG,CH,CI,CK,CL,CM,CN,CO,CR,CU,CV,CW,CX,CY,CZ,DE,DJ,DK,DM,DO,DZ,EC,EE,EG,EH,ER,ES,ET,FI,FJ,FK,FM,FO,FR,GA,GB,GD,GE,GF,GG,GH,GI,GL,GM,GN,GP,GQ,GR,GS,GT,GU,GW,GY,HK,HM,HN,HR,HT,HU,ID,IE,IL,IM,IN,IO,IQ,IR,IS,IT,JE,JM,JO,JP,KE,KG,KH,KI,KM,KN,KP,KR,KW,KY,KZ,LA,LB,LC,LI,LK,LR,LS,LT,LU,LV,LY,MA,MC,MD,ME,MF,MG,MH,MK,ML,MM,MN,MO,MP,MQ,MR,MS,MT,MU,MV,MW,MX,MY,MZ,NA,NC,NE,NF,NG,NI,NL,NO,NP,NR,NU,NZ,OM,PA,PE,PF,PG,PH,PK,PL,PM,PN,PR,PS,PT,PW,PY,QA,RE,RO,RS,RU,RW,SA,SB,SC,SD,SE,SG,SH,SI,SJ,SK,SL,SM,SN,SO,SR,SS,ST,SV,SX,SY,SZ,TC,TD,TF,TG,TH,TJ,TK,TL,TM,TN,TO,TR,TT,TV,TW,TZ,UA,UG,UM,US,UY,UZ,VA,VC,VE,VG,VI,VN,VU,WF,WS,YE,YT,ZA,ZM,ZW","isPaid":false,"unlisted":false}