{"key":"Salz7uGp72c","title":"The Theory of Everything - Official Trailer (Universal Pictures) HD","description":"The Official Trailer for The Theory of Everything In Cinemas New Year's Day, 2015 http://www.thetheoryofeverythingmovie... Subscribe to our channel - http://po.st/UniversalPicturesUK The Theory of Everything is the story of the most brilliant and celebrated physicist of our time, Stephen Hawking, and Jane Wilde the arts student he fell in love with whilst studying at Cambridge in the 1960s. Little was expected from Stephen Hawking, a bright but shiftless student of cosmology, given just two years to live following the diagnosis of a fatal illness at 21 years of age. He became galvanized, however, by the love of fellow Cambridge student, Jane Wilde, and he went on to be called the successor to Einstein, as well as a husband and father to their three children. Over the course of their marriage as Stephen’s body collapsed and his academic renown soared, fault lines were exposed that tested the lineaments of their relationship and dramatically altered the course of both of their lives. Universal Pictures UK “Universal Pictures” “Official” “New” “International” “New Trailers” “trailers HD” “HD Trailers” “2015 Trailers” “2015” \"The Theory of Everything\" \"Eddie Redmayne\" \"Stephen Hawking\" \"Felicity Jones\" \"Space\" \"TIme\" The Theory Of Everything Official Trailer","publishedDate":"Published on Aug 6, 2014","viewCount":5830639,"noOfLikes":38493,"noOfDislikes":1771,"relatedURL":["/watch?v=vQwCxGe_jD4","/watch?v=pZwv6h-LhTw","/watch?v=Q1HO07bKGhU","/watch?v=8RHU0X5CYpU","/watch?v=A86JGbBEaBk","/watch?v=7McSiK7IrDw","/watch?v=VcSosCe0B-A","/watch?v=V602GMSSo0Y","/watch?v=ixjQ58-wkAk","/watch?v=rMp896hfp74","/watch?v=U_ytm34YVCU","/watch?v=Yj0l7iGKh8g","/watch?v=hg37MLNj16Q","/watch?v=uCy_jOtL_KE","/watch?v=GrXe8YDbzYs","/watch?v=Eh6nYOhItOM","/watch?v=t-v1_OttK4A","/watch?v=CQERFnGvi_A","/watch?v=cQszhfoP_WI","/watch?v=5zL3YJKygd4"],"category":"","comments":[],"latitude":0.0,"longitude":0.0,"duration":"PT2M47S","channelID":"UCQLBOKpgXrSj3nPU-YC3K9Q","authorYTURL":"http://www.youtube.com/user/universalpicturesuk","authorGPlusURL":"https://plus.google.com/104218025433086661935","isFamilyFriendly":true,"regionAllowed":"AD,AE,AF,AG,AI,AL,AM,AO,AQ,AR,AS,AT,AU,AW,AX,AZ,BA,BB,BD,BE,BF,BG,BH,BI,BJ,BL,BM,BN,BO,BQ,BR,BS,BT,BV,BW,BY,BZ,CA,CC,CD,CF,CG,CH,CI,CK,CL,CM,CN,CO,CR,CU,CV,CW,CX,CY,CZ,DE,DJ,DK,DM,DO,DZ,EC,EE,EG,EH,ER,ES,ET,FI,FJ,FK,FM,FO,FR,GA,GB,GD,GE,GF,GG,GH,GI,GL,GM,GN,GP,GQ,GR,GS,GT,GU,GW,GY,HK,HM,HN,HR,HT,HU,ID,IE,IL,IM,IN,IO,IQ,IR,IS,IT,JE,JM,JO,JP,KE,KG,KH,KI,KM,KN,KP,KR,KW,KY,KZ,LA,LB,LC,LI,LK,LR,LS,LT,LU,LV,LY,MA,MC,MD,ME,MF,MG,MH,MK,ML,MM,MN,MO,MP,MQ,MR,MS,MT,MU,MV,MW,MX,MY,MZ,NA,NC,NE,NF,NG,NI,NL,NO,NP,NR,NU,NZ,OM,PA,PE,PF,PG,PH,PK,PL,PM,PN,PR,PS,PT,PW,PY,QA,RE,RO,RS,RU,RW,SA,SB,SC,SD,SE,SG,SH,SI,SJ,SK,SL,SM,SN,SO,SR,SS,ST,SV,SX,SY,SZ,TC,TD,TF,TG,TH,TJ,TK,TL,TM,TN,TO,TR,TT,TV,TW,TZ,UA,UG,UM,US,UY,UZ,VA,VC,VE,VG,VI,VN,VU,WF,WS,YE,YT,ZA,ZM,ZW","isPaid":false,"unlisted":false}